{"cameraMode":{"drawMode":0,"name":"Shaded","section":"Shading Mode"},"sceneLighting":false,"audioPlay":false,"sceneViewState":{"m_AlwaysRefresh":false,"showFog":true,"showSkybox":false,"showFlares":true,"showImageEffects":true,"showParticleSystems":true,"showVisualEffectGraphs":true,"m_FxEnabled":true},"in2DMode":false,"pivot":{"x":0.0,"y":1.2734296321868897,"z":0.730785608291626},"rotation":{"x":-0.08628525584936142,"y":0.9063430428504944,"z":-0.3467470407485962,"w":-0.22553510963916779},"size":3.975940704345703,"orthographic":false}